README.rst
setup.py
infra_scraper/__init__.py
infra_scraper/cli.py
infra_scraper/constants.py
infra_scraper/constructors.py
infra_scraper/exceptions.py
infra_scraper/main.py
infra_scraper/server.py
infra_scraper/utils.py
infra_scraper.egg-info/PKG-INFO
infra_scraper.egg-info/SOURCES.txt
infra_scraper.egg-info/dependency_links.txt
infra_scraper.egg-info/entry_points.txt
infra_scraper.egg-info/requires.txt
infra_scraper.egg-info/top_level.txt
infra_scraper/input/__init__.py
infra_scraper/input/amazon.py
infra_scraper/input/base.py
infra_scraper/input/heat.py
infra_scraper/input/kubernetes.py
infra_scraper/input/openstack.py
infra_scraper/input/reclass.py
infra_scraper/input/saltstack.py
infra_scraper/input/terraform.py
infra_scraper/output/__init__.py
infra_scraper/output/base.py
infra_scraper/output/count.py
infra_scraper/output/enc.py
infra_scraper/output/raw.py
infra_scraper/output/vis.py
infra_scraper/storage/__init__.py
infra_scraper/storage/base.py
infra_scraper/storage/etcd.py
infra_scraper/storage/file.py