Metadata-Version: 1.1
Name: infra-scraper
Version: 0.2
Summary: Infrastrucutre metadata scraper with support for multiple
Home-page: https://github.com/cznewt/infra-scraper/
Author: Aleš Komárek
Author-email: ales.komarek@newt.cz
License: Apache License, Version 2.0
Platform: UNKNOWN
Classifier: Intended Audience :: System Administrators
Classifier: License :: OSI Approved :: Apache Software License
Classifier: Operating System :: POSIX :: Linux
Classifier: Programming Language :: Python
Classifier: Programming Language :: Python :: Implementation :: CPython
Classifier: Programming Language :: Python :: 3
Classifier: Programming Language :: Python :: 3.6
